ccproxy/__main__.py
ccproxy/api/__init__.py
ccproxy/api/app.py
ccproxy/api/bootstrap.py
ccproxy/api/decorators.py
ccproxy/api/dependencies.py
ccproxy/api/format_validation.py
ccproxy/api/middleware/__init__.py
ccproxy/api/middleware/cors.py
ccproxy/api/middleware/errors.py
ccproxy/api/middleware/hooks.py
ccproxy/api/middleware/normalize_headers.py
ccproxy/api/middleware/request_id.py
ccproxy/api/middleware/streaming_hooks.py
ccproxy/api/routes/__init__.py
ccproxy/api/routes/health.py
ccproxy/api/routes/plugins.py
ccproxy/auth/__init__.py
ccproxy/auth/bearer.py
ccproxy/auth/dependencies.py
ccproxy/auth/exceptions.py
ccproxy/auth/manager.py
ccproxy/auth/managers/__init__.py
ccproxy/auth/managers/base.py
ccproxy/auth/managers/base_enhanced.py
ccproxy/auth/managers/token_snapshot.py
ccproxy/auth/models/__init__.py
ccproxy/auth/models/base.py
ccproxy/auth/models/credentials.py
ccproxy/auth/oauth/__init__.py
ccproxy/auth/oauth/base.py
ccproxy/auth/oauth/cli_errors.py
ccproxy/auth/oauth/flows.py
ccproxy/auth/oauth/protocol.py
ccproxy/auth/oauth/registry.py
ccproxy/auth/oauth/router.py
ccproxy/auth/oauth/routes.py
ccproxy/auth/oauth/session.py
ccproxy/auth/oauth/templates.py
ccproxy/auth/storage/__init__.py
ccproxy/auth/storage/base.py
ccproxy/auth/storage/generic.py
ccproxy/cli/__init__.py
ccproxy/cli/_settings_help.py
ccproxy/cli/decorators.py
ccproxy/cli/helpers.py
ccproxy/cli/main.py
ccproxy/cli/commands/__init__.py
ccproxy/cli/commands/auth.py
ccproxy/cli/commands/plugins.py
ccproxy/cli/commands/serve.py
ccproxy/cli/commands/status.py
ccproxy/cli/commands/config/__init__.py
ccproxy/cli/commands/config/commands.py
ccproxy/cli/commands/config/schema_commands.py
ccproxy/cli/options/__init__.py
ccproxy/cli/options/claude_options.py
ccproxy/cli/options/core_options.py
ccproxy/cli/options/security_options.py
ccproxy/cli/options/server_options.py
ccproxy/config/__init__.py
ccproxy/config/core.py
ccproxy/config/env_generator.py
ccproxy/config/runtime.py
ccproxy_api-0.2.0.dist-info/METADATA
ccproxy_api-0.2.0.dist-info/WHEEL
ccproxy_api-0.2.0.dist-info/entry_points.txt
ccproxy_api-0.2.0.dist-info/licenses/LICENSE
ccproxy_api-0.2.0.dist-info/RECORD
