Metadata-Version: 2.4
Name: ccproxy-api
Version: 0.2.0
Summary: API server that provides an Anthropic and OpenAI compatible interface over Claude Code, allowing to use your Claude OAuth account or over the API.
License-File: LICENSE
Requires-Python: >=3.11
Requires-Dist: aiofiles>=24.1.0
Requires-Dist: fastapi[standard]>=0.115.14
Requires-Dist: httpx[http2]>=0.28.1
Requires-Dist: packaging>=25.0
Requires-Dist: pydantic-settings>=2.4.0
Requires-Dist: pydantic>=2.8.0
Requires-Dist: pyjwt>=2.10.1
Requires-Dist: rich-toolkit>=0.14.8
Requires-Dist: rich>=13.0.0
Requires-Dist: sortedcontainers>=2.4.0
Requires-Dist: structlog>=25.4.0
Requires-Dist: typer>=0.16.0
Requires-Dist: typing-extensions>=4.0.0
Requires-Dist: uvicorn>=0.34.0
Provides-Extra: plugins-claude
Requires-Dist: claude-agent-sdk>=0.1.0; extra == 'plugins-claude'
Requires-Dist: qrcode>=8.2; extra == 'plugins-claude'
Provides-Extra: plugins-codex
Requires-Dist: pyjwt>=2.10.1; extra == 'plugins-codex'
Requires-Dist: qrcode>=8.2; extra == 'plugins-codex'
Provides-Extra: plugins-mcp
Requires-Dist: fastapi-mcp>=0.3.7; extra == 'plugins-mcp'
Provides-Extra: plugins-metrics
Requires-Dist: prometheus-client>=0.22.1; extra == 'plugins-metrics'
Provides-Extra: plugins-storage
Requires-Dist: duckdb-engine>=0.17.0; extra == 'plugins-storage'
Requires-Dist: duckdb<1.4.0,>=1.1.0; extra == 'plugins-storage'
Requires-Dist: sqlalchemy>=2.0.0; extra == 'plugins-storage'
Requires-Dist: sqlmodel>=0.0.24; extra == 'plugins-storage'
Provides-Extra: plugins-tui
Requires-Dist: aioconsole>=0.8.1; extra == 'plugins-tui'
Requires-Dist: textual>=3.7.1; extra == 'plugins-tui'
